pytrait/__init__.py
pytrait/errors.py
pytrait/impl.py
pytrait/struct.py
pytrait/trait.py
pytrait-0.0.3.dist-info/LICENSE.txt
pytrait-0.0.3.dist-info/METADATA
pytrait-0.0.3.dist-info/WHEEL
pytrait-0.0.3.dist-info/top_level.txt
pytrait-0.0.3.dist-info/RECORD
